{
  "values": {
    "strength": "75.2",
    "satStrength": "1",
    "satPerNoise": "0",
    "noiseSize": "0",
    "blurriness": "13",
    "opacity": "0.5",
    "shadowThreshold": "0.48",
    "shadowFade": "0.43",
    "highlightThreshold": "0.66",
    "highlightFade": "0.6",
    "ignoreAlphaStrength": "100",
    "brightness": "6",
    "contrast": "39",
    "saturationAdj": "-100",
    "warmth": "-500",
    "sharpen": "4",
    "adjColorTolerance": "0",
    "adjColorFade": "20",
    "adjShadowThreshold": "0.5",
    "adjShadowFade": "0",
    "adjHighlightThreshold": "0.66",
    "adjHighlightFade": "0",
    "hdrTolerance": "0.6",
    "hdrAmount": "85",
    "aberrationAmount": "639",
    "caRadius": "0",
    "caFalloff": "366",
    "aberrationBlur": "0",
    "blurAmount": "100",
    "blurColorTolerance": "10",
    "blurColorFade": "20",
    "blurShadowThreshold": "0.48",
    "blurShadowFade": "0",
    "blurHighlightThreshold": "0.75",
    "blurHighlightFade": "0.78",
    "ditherBitDepth": "8",
    "ditherPaletteSize": "256",
    "ditherStrength": "1000",
    "ditherScale": "1",
    "ditherColorTolerance": "10",
    "ditherColorFade": "20",
    "ditherShadowThreshold": "0",
    "ditherShadowFade": "0",
    "ditherHighlightThreshold": "0",
    "ditherHighlightFade": "0",
    "corruptionIterations": "500",
    "corruptionResScale": "62",
    "cellLevels": "12",
    "cellBias": "0.19",
    "cellGamma": "1.0",
    "cellEdgeStr": "1",
    "cellEdgeThick": "1.4",
    "halftoneSize": "4",
    "halftoneIntensity": "1",
    "halftoneSharpness": "0",
    "halftoneColorTolerance": "10",
    "halftoneColorFade": "20",
    "halftoneShadowThreshold": "0",
    "halftoneShadowFade": "0",
    "halftoneHighlightThreshold": "0",
    "halftoneHighlightFade": "0",
    "bilateralRadius": "5",
    "bilateralColorSig": "0.1",
    "bilateralSpatialSig": "2.0",
    "bilateralIter": "1",
    "bilateralColorTolerance": "10",
    "bilateralColorFade": "20",
    "bilateralShadowThreshold": "0",
    "bilateralShadowFade": "0",
    "bilateralHighlightThreshold": "0",
    "bilateralHighlightFade": "0",
    "hoverZoomSlider": "1"
  },
  "checks": {
    "enableShadows": true,
    "enableHighlights": true,
    "ignoreAlphaToggle": true,
    "adjColorExclude": false,
    "adjLumaMask": true,
    "blurEnable": true,
    "blurColorExclude": false,
    "blurLumaMask": true,
    "ditherEnable": true,
    "ditherColorExclude": false,
    "ditherLumaMask": false,
    "corruptionEnable": true,
    "cellEnable": false,
    "cellEdgeEnable": false,
    "cellColorPreserve": false,
    "halftoneEnable": false,
    "halftoneGray": false,
    "halftoneScreenLock": true,
    "halftoneInvert": false,
    "halftoneColorExclude": false,
    "halftoneLumaMask": false,
    "bilateralEnable": false,
    "bilateralHighPrec": true,
    "bilateralColorExclude": false,
    "bilateralLumaMask": false,
    "": true
  },
  "selects": {
    "noiseType": "1",
    "blendMode": "0",
    "blurType": "0",
    "ditherType": "0",
    "corruptionAlgorithm": "2",
    "cellQuantMode": "1",
    "cellBandMap": "0",
    "cellEdgeMethod": "1",
    "halftonePattern": "0",
    "halftoneColorMode": "0",
    "halftoneSample": "0",
    "bilateralKernel": "0",
    "bilateralEdgeMode": "0"
  },
  "renderOrder": [
    "noise",
    "adjust",
    "hdr",
    "ca",
    "blur",
    "cell",
    "halftone",
    "bilateral",
    "dither",
    "corruption"
  ],
  "layerVisibility": {
    "noise": true,
    "adjust": true,
    "hdr": true,
    "ca": true,
    "blur": true,
    "cell": true,
    "halftone": true,
    "bilateral": true,
    "dither": true,
    "corruption": true
  },
  "upscaleFactor": 3,
  "caCenter": {
    "x": 0.41278810408921934,
    "y": 0.40938135644307105
  }
}